GOFevaluation/__init__.py
GOFevaluation/evaluator_base.py
GOFevaluation/evaluators_1d.py
GOFevaluation/evaluators_nd.py
GOFevaluation/gof_test.py
GOFevaluation/utils.py
tests/__init__.py
tests/test_evaluators_1d.py
tests/test_evaluators_nd.py
tests/test_gof_test.py
tests/test_plots.py
tests/test_utils.py
GOFevaluation-0.1.6.dist-info/LICENSE
GOFevaluation-0.1.6.dist-info/METADATA
GOFevaluation-0.1.6.dist-info/WHEEL
GOFevaluation-0.1.6.dist-info/top_level.txt
GOFevaluation-0.1.6.dist-info/RECORD
