Metadata-Version: 2.1
Name: GOFevaluation
Version: 0.1.6
Summary: Evaluate the Goodness-of-Fit(GOF) for binned or unbinned data.
Home-page: https://github.com/XENONnT/GOFevaluation
Author: GOFevaluation contributors, the XENON collaboration
License: UNKNOWN
Platform: UNKNOWN
Classifier: Programming Language :: Python :: 3.8
Classifier: Programming Language :: Python :: 3.9
Classifier: License :: OSI Approved :: BSD License
Classifier: Operating System :: OS Independent
Requires-Python: >=3.8
Requires-Dist: numpy
Requires-Dist: scipy
Requires-Dist: scikit-learn
Requires-Dist: matplotlib
Requires-Dist: pandas
Requires-Dist: iminuit
